src/__init__.py
src/cli.py
src/logger.py
src/settings.py
src/service/__init__.py
src/service/collector.py
src/service/summarizer.py
pulldoc-0.2.2.dist-info/METADATA
pulldoc-0.2.2.dist-info/WHEEL
pulldoc-0.2.2.dist-info/entry_points.txt
pulldoc-0.2.2.dist-info/licenses/LICENSE
pulldoc-0.2.2.dist-info/RECORD
