Metadata-Version: 2.4
Name: pulldoc
Version: 0.2.2
Summary: Generate fix patterns & issue templates from PR history
Project-URL: Homepage, https://github.com/ppspps824/pulldoc
Project-URL: Bug Tracker, https://github.com/ppspps824/pulldoc/issues
License-File: LICENSE
Classifier: License :: OSI Approved :: MIT License
Classifier: Operating System :: OS Independent
Classifier: Programming Language :: Python :: 3
Requires-Python: >=3.12
Requires-Dist: boto3>=1.38.31
Requires-Dist: google-generativeai>=0.8.5
Requires-Dist: litellm>=1.36.0
Requires-Dist: pydantic-settings>=2.0
Requires-Dist: pydantic>=2.7
Requires-Dist: pygithub>=2.3
Requires-Dist: tenacity>=9.1.2
Requires-Dist: typer>=0.12.3
Provides-Extra: dev
Requires-Dist: black; extra == 'dev'
Requires-Dist: isort; extra == 'dev'
Requires-Dist: pytest; extra == 'dev'
Requires-Dist: pytest-cov; extra == 'dev'
